censys/__main__.py
censys/asm/__init__.py
censys/asm/api.py
censys/asm/assets/__init__.py
censys/asm/assets/assets.py
censys/asm/assets/certificates.py
censys/asm/assets/domains.py
censys/asm/assets/hosts.py
censys/asm/assets/object_storages.py
censys/asm/assets/subdomains.py
censys/asm/assets/web_entities.py
censys/asm/beta.py
censys/asm/client.py
censys/asm/clouds.py
censys/asm/inventory.py
censys/asm/logbook.py
censys/asm/risks.py
censys/asm/saved_queries.py
censys/asm/seeds.py
censys/cli/__init__.py
censys/cli/args.py
censys/cli/commands/__init__.py
censys/cli/commands/account.py
censys/cli/commands/asm.py
censys/cli/commands/config.py
censys/cli/commands/hnri.py
censys/cli/commands/search.py
censys/cli/commands/subdomains.py
censys/cli/commands/view.py
censys/cli/data/certificates_autocomplete.json
censys/cli/data/hosts_autocomplete.json
censys/cli/utils.py
censys/common/__init__.py
censys/common/base.py
censys/common/config.py
censys/common/deprecation.py
censys/common/exceptions.py
censys/common/types.py
censys/common/utils.py
censys/common/version.py
censys/py.typed
censys/search/__init__.py
censys/search/client.py
censys/search/v1/__init__.py
censys/search/v1/api.py
censys/search/v1/data.py
censys/search/v2/__init__.py
censys/search/v2/api.py
censys/search/v2/certs.py
censys/search/v2/hosts.py
censys-2.2.19.dist-info/METADATA
censys-2.2.19.dist-info/WHEEL
censys-2.2.19.dist-info/entry_points.txt
censys-2.2.19.dist-info/licenses/LICENSE
censys-2.2.19.dist-info/RECORD
