Metadata-Version: 2.4
Name: censys
Version: 2.2.19
Summary: An easy-to-use and lightweight API wrapper for Censys APIs (censys.io).
License: Apache-2.0
License-File: LICENSE
Keywords: censys,api,search,attack surface management
Author: Censys, Inc.
Author-email: support@censys.io
Requires-Python: >=3.8,<4.0
Classifier: Development Status :: 5 - Production/Stable
Classifier: Environment :: Console
Classifier: Intended Audience :: Developers
Classifier: Intended Audience :: Information Technology
Classifier: Intended Audience :: Science/Research
Classifier: Intended Audience :: System Administrators
Classifier: License :: OSI Approved :: Apache Software License
Classifier: Natural Language :: English
Classifier: Operating System :: OS Independent
Classifier: Programming Language :: Python
Classifier: Programming Language :: Python :: 3
Classifier: Programming Language :: Python :: 3.8
Classifier: Programming Language :: Python :: 3.9
Classifier: Programming Language :: Python :: 3.10
Classifier: Programming Language :: Python :: 3.11
Classifier: Programming Language :: Python :: 3.12
Classifier: Programming Language :: Python :: 3.13
Classifier: Programming Language :: Python :: 3.14
Classifier: Programming Language :: Python :: 3 :: Only
Classifier: Programming Language :: Python :: Implementation :: PyPy
Classifier: Topic :: Documentation :: Sphinx
Classifier: Topic :: Internet
Classifier: Topic :: Internet :: WWW/HTTP :: HTTP Servers
Classifier: Topic :: Internet :: WWW/HTTP :: Indexing/Search
Classifier: Topic :: Scientific/Engineering :: Information Analysis
Classifier: Topic :: Security
Classifier: Topic :: Software Development :: Libraries :: Python Modules
Classifier: Topic :: System :: Networking
Classifier: Topic :: Utilities
Classifier: Typing :: Typed
Requires-Dist: argcomplete (>=2.0.0,<4.0.0)
Requires-Dist: backoff (>=2.0.0,<3.0.0)
Requires-Dist: requests (>=2.29.0)
Requires-Dist: rich (>=10.16.2)
Requires-Dist: urllib3 (<3.0.0)
Project-URL: Censys Homepage, https://censys.io/
Project-URL: Censys Search, https://search.censys.io/
Project-URL: Changelog, https://github.com/censys/censys-python/releases
Project-URL: Discussions, https://github.com/censys/censys-python/discussions
Project-URL: Documentation, https://censys-python.rtfd.io
Project-URL: Source, https://github.com/censys/censys-python
Project-URL: Tracker, https://github.com/censys/censys-python/issues
